dob_viewer/__init__.py
dob_viewer/config/__init__.py
dob_viewer/config/custom_paste.py
dob_viewer/config/editor_keys.py
dob_viewer/config/json_sublist.py
dob_viewer/ptkui/__init__.py
dob_viewer/ptkui/dialog_overlay.py
dob_viewer/ptkui/re_confirm.py
dob_viewer/ptkui/various_lexers.py
dob_viewer/traverser/__init__.py
dob_viewer/traverser/action_manager.py
dob_viewer/traverser/carousel.py
dob_viewer/traverser/clipboard_edit.py
dob_viewer/traverser/content_lexer.py
dob_viewer/traverser/edits_manager.py
dob_viewer/traverser/exceptions.py
dob_viewer/traverser/facts_manager.py
dob_viewer/traverser/facts_mgr_fact_dec.py
dob_viewer/traverser/facts_mgr_fact_inc.py
dob_viewer/traverser/facts_mgr_gap.py
dob_viewer/traverser/facts_mgr_jump.py
dob_viewer/traverser/facts_mgr_jump_time.py
dob_viewer/traverser/facts_mgr_rift.py
dob_viewer/traverser/facts_mgr_rift_dec.py
dob_viewer/traverser/facts_mgr_rift_inc.py
dob_viewer/traverser/group_chained.py
dob_viewer/traverser/interface_keys.py
dob_viewer/traverser/key_action_map.py
dob_viewer/traverser/redo_undo_edit.py
dob_viewer/traverser/save_confirmer.py
dob_viewer/traverser/start_end_edit.py
dob_viewer/traverser/update_handler.py
dob_viewer/traverser/zone_content.py
dob_viewer/traverser/zone_details.py
dob_viewer/traverser/zone_details_time_end.py
dob_viewer/traverser/zone_details_time_start.py
dob_viewer/traverser/zone_helpful.py
dob_viewer/traverser/zone_lowdown.py
dob_viewer/traverser/zone_manager.py
dob_viewer/traverser/zone_streamer.py
dob_viewer-1.2.8.dist-info/LICENSE
dob_viewer-1.2.8.dist-info/METADATA
dob_viewer-1.2.8.dist-info/WHEEL
dob_viewer-1.2.8.dist-info/RECORD
