Metadata-Version: 2.1
Name: dob-viewer
Version: 1.2.8
Summary: journal and time tracker, supercharged for the terminal
License: GPLv3+
Keywords: journal,diary,timesheet,timetrack,jrnl,rednotebook,todo.txt,prjct,hamster,fact
Author: Landon Bouma
Author-email: doblabs@tallybark.com
Maintainer: Tally Bark LLC
Maintainer-email: doblabs@tallybark.com
Requires-Python: >=3.8.1,<4.0.0
Classifier: Development Status :: 5 - Production/Stable
Classifier: Environment :: Console
Classifier: Intended Audience :: End Users/Desktop
Classifier: License :: Other/Proprietary License
Classifier: Natural Language :: English
Classifier: Operating System :: OS Independent
Classifier: Programming Language :: Python :: 3
Classifier: Programming Language :: Python :: 3.9
Classifier: Programming Language :: Python :: 3.10
Classifier: Programming Language :: Python :: 3.11
Classifier: Programming Language :: Python :: 3.12
Classifier: Topic :: Software Development :: Libraries :: Python Modules
Provides-Extra: readthedocs
Requires-Dist: Inflector (>=3.0.1,<4.0.0)
Requires-Dist: click-hotoffthehamster (>0)
Requires-Dist: dob-bright (>0)
Requires-Dist: dob-prompt (>0)
Requires-Dist: easy-as-pypi-getver (>0)
Requires-Dist: easy-as-pypi-termio (>0)
Requires-Dist: nark (>0)
Requires-Dist: prompt-toolkit (>=3.0.5,<4.0.0)
Requires-Dist: pygments (>=2.6.1,<3.0.0)
Requires-Dist: sortedcontainers (>=2.1.0,<3.0.0)
Requires-Dist: sphinx (>=6.2.1,<7.0.0) ; (python_version >= "3.8" and python_version < "3.9") and (extra == "readthedocs")
Requires-Dist: sphinx (>=7.2.6,<8.0.0) ; (python_version >= "3.9" and python_version < "4.0") and (extra == "readthedocs")
Requires-Dist: sphinx-rtd-theme (>=2.0.0rc4,<3.0.0) ; extra == "readthedocs"
Requires-Dist: tomli (>=2.0.1) ; extra == "readthedocs"
Project-URL: documentation, https://dob-viewer.readthedocs.io/en/latest
Project-URL: download, https://pypi.org/project/dob-viewer/#files
Project-URL: homepage, https://github.com/doblabs/dob-viewer
Project-URL: history, https://github.com/doblabs/dob-viewer/blob/release/HISTORY.rst
Project-URL: issues, https://github.com/doblabs/dob-viewer/issues
